openhab/__init__.py
openhab/client.py
openhab/command_types.py
openhab/config.py
openhab/exceptions.py
openhab/items.py
openhab/oauth2_helper.py
openhab/py.typed
openhab/rules.py
python_openhab-2.20.2.dist-info/licenses/LICENSE
tests/__init__.py
tests/conftest.py
tests/test_basic.py
tests/test_oauth.py
python_openhab-2.20.2.dist-info/METADATA
python_openhab-2.20.2.dist-info/WHEEL
python_openhab-2.20.2.dist-info/top_level.txt
python_openhab-2.20.2.dist-info/RECORD
