Metadata-Version: 2.4
Name: python-openhab
Version: 2.20.2
Summary: python library for accessing the openHAB REST API
Author-email: Georges Toth <georges@trypill.org>
License: AGPLv3+
Project-URL: Homepage, https://github.com/sim0nx/python-openhab
Project-URL: Download, https://github.com/sim0nx/python-openhab
Project-URL: Tracker, https://github.com/sim0nx/python-openhab/issues
Project-URL: Documentation, http://python-openhab.readthedocs.io/en/latest/?badge=latest
Project-URL: Source, https://github.com/sim0nx/python-openhab
Keywords: openHAB
Classifier: Development Status :: 5 - Production/Stable
Classifier: License :: OSI Approved :: GNU Affero General Public License v3 or later (AGPLv3+)
Classifier: Intended Audience :: Developers
Classifier: Operating System :: OS Independent
Classifier: Programming Language :: Python :: 3 :: Only
Classifier: Programming Language :: Python :: 3.9
Classifier: Programming Language :: Python :: 3.10
Classifier: Programming Language :: Python :: 3.11
Classifier: Programming Language :: Python :: 3.12
Classifier: Programming Language :: Python :: 3.13
Requires-Python: >=3.9
License-File: LICENSE
Requires-Dist: python-dateutil~=2.8
Requires-Dist: pydantic<3
Requires-Dist: Authlib~=1.2
Requires-Dist: httpx~=0.24
Dynamic: license-file
